opencdms/__init__.py
opencdms/models/__init__.py
opencdms/models/cdm.py
opencdms/provider/__init__.py
opencdms/provider/base.py
opencdms/provider/opencdmsdb/__init__.py
opencdms/utils/__init__.py
tests/__init__.py
tests/integration/__init__.py
tests/integration/models/__init__.py
tests/integration/providers/__init__.py
tests/unit/__init__.py
pyopencdms-0.1.0.dist-info/AUTHORS.md
pyopencdms-0.1.0.dist-info/LICENSE
pyopencdms-0.1.0.dist-info/METADATA
pyopencdms-0.1.0.dist-info/WHEEL
pyopencdms-0.1.0.dist-info/top_level.txt
pyopencdms-0.1.0.dist-info/RECORD
