Metadata-Version: 2.1
Name: pyopencdms
Version: 0.1.0
Summary: OpenCDMS Python package
Home-page: https://github.com/opencdms/pyopencdms
Author: OpenCDMS
Author-email: info@opencdms.org
License: MIT license
Keywords: opencdms
Classifier: Development Status :: 2 - Pre-Alpha
Classifier: Intended Audience :: Developers
Classifier: License :: OSI Approved :: MIT License
Classifier: Natural Language :: English
Classifier: Programming Language :: Python :: 3
Classifier: Programming Language :: Python :: 3.7
Classifier: Programming Language :: Python :: 3.8
Classifier: Programming Language :: Python :: 3.9
Requires-Python: >=3.7
License-File: LICENSE
License-File: AUTHORS.md
Requires-Dist: geoalchemy2 (>=0.13.0)
